{"name":{"common":"Mauritius","official":"Republic of Mauritius","native":{"eng":{"official":"Republic of Mauritius","common":"Mauritius"},"fra":{"official":"République de Maurice","common":"Maurice"},"mfe":{"official":"Republik Moris","common":"Moris"}}},"altSpellings":["MU","Republic of Mauritius","République de Maurice"],"area":2040,"borders":[],"capital":"Port Louis","demonym":"Mauritian","flag":"","geoJSON":{},"languages":{"eng":"English","fra":"French","mfe":"Mauritian Creole"},"latlng":[-20.28333333,57.55],"nativeName":"Maurice","population":1261208,"provinces":["Agalega Islands","Black River","Cargados Carajos Shoals","Flacq","Grand Port","Moka","Pamplemousses","Plaines Wilhems","Port Louis","Riviere du Rempart","Rodrigues","Savanne"],"region":"Africa","subregion":"Eastern Africa","timezones":["UTC+04:00"],"tld":[".mu"],"translations":{"deu":{"official":"Republik Mauritius","common":"Mauritius"},"fra":{"official":"République de Maurice","common":"Île Maurice"},"hrv":{"official":"Republika Mauricijus","common":"Mauricijus"},"ita":{"official":"Repubblica di Mauritius","common":"Mauritius"},"jpn":{"official":"モーリシャス共和国","common":"モーリシャス"},"nld":{"official":"Republiek Mauritius","common":"Mauritius"},"por":{"official":"República das Maurícias","common":"Maurício"},"rus":{"official":"Республика Маврикий","common":"Маврикий"},"spa":{"official":"República de Mauricio","common":"Mauricio"},"fin":{"official":"Mauritiuksen tasavalta","common":"Mauritius"}},"wiki":"http://en.wikipedia.org/wiki/mauritius","currency":["MUR"],"callingCode":["230"],"landlocked":false,"codes":{"cca2":"MU","ccn3":"480","cca3":"MUS","cioc":"MRI"}}